behavioral_signals_swagger_client/__init__.py
behavioral_signals_swagger_client/api_client.py
behavioral_signals_swagger_client/configuration.py
behavioral_signals_swagger_client/rest.py
behavioral_signals_swagger_client/api/__init__.py
behavioral_signals_swagger_client/api/administration_api.py
behavioral_signals_swagger_client/api/api_status_api.py
behavioral_signals_swagger_client/api/behavioral_profiling_api.py
behavioral_signals_swagger_client/api/call_processing_api.py
behavioral_signals_swagger_client/models/__init__.py
behavioral_signals_swagger_client/models/agent.py
behavioral_signals_swagger_client/models/agent_behavioral_skill.py
behavioral_signals_swagger_client/models/array_of_agent_behavioral_skills.py
behavioral_signals_swagger_client/models/array_of_agents.py
behavioral_signals_swagger_client/models/array_of_behavioral_skill_agents.py
behavioral_signals_swagger_client/models/array_of_behavioral_skill_associations.py
behavioral_signals_swagger_client/models/array_of_behavioral_skill_customer.py
behavioral_signals_swagger_client/models/array_of_behavioral_skills.py
behavioral_signals_swagger_client/models/array_of_behavioral_skills_i_ds.py
behavioral_signals_swagger_client/models/array_of_behavioral_skills_ids.py
behavioral_signals_swagger_client/models/array_of_customers.py
behavioral_signals_swagger_client/models/array_of_id_patches.py
behavioral_signals_swagger_client/models/array_of_portfolio_ids.py
behavioral_signals_swagger_client/models/array_of_portfolio_speakers.py
behavioral_signals_swagger_client/models/array_of_processes.py
behavioral_signals_swagger_client/models/authorized.py
behavioral_signals_swagger_client/models/behavioral_skill.py
behavioral_signals_swagger_client/models/behavioral_skill_agent.py
behavioral_signals_swagger_client/models/behavioral_skill_associations.py
behavioral_signals_swagger_client/models/behavioral_skill_id.py
behavioral_signals_swagger_client/models/body.py
behavioral_signals_swagger_client-4.5.12.dist-info/METADATA
behavioral_signals_swagger_client-4.5.12.dist-info/WHEEL
behavioral_signals_swagger_client-4.5.12.dist-info/top_level.txt
behavioral_signals_swagger_client-4.5.12.dist-info/RECORD
