Metadata-Version: 2.1
Name: behavioral-signals-swagger-client
Version: 4.5.12
Summary: Oliver API
Home-page: UNKNOWN
Author-email: api@behavioralsignals.com
License: UNKNOWN
Keywords: Swagger,Oliver API
Platform: UNKNOWN
Requires-Dist: certifi
Requires-Dist: python-dateutil
Requires-Dist: six>=1.10
Requires-Dist: urllib3>=1.15
